vexshield/__init__.py
vexshield-0.1.0.dist-info/METADATA
vexshield-0.1.0.dist-info/WHEEL
vexshield-0.1.0.dist-info/RECORD
