Metadata-Version: 2.4
Name: vexshield
Version: 0.1.0
Summary: Comprehensive supply chain security platform with reachability analysis
Project-URL: Homepage, https://vexshield.com
Project-URL: Repository, https://github.com/vexshield/vexshield
Author-email: VexShield <hello@vexshield.com>
License: BSL-1.1
Keywords: sbom,sca,security,supply-chain,vulnerability
Classifier: Development Status :: 2 - Pre-Alpha
Classifier: Intended Audience :: Developers
Classifier: Topic :: Security
Classifier: Topic :: Software Development :: Quality Assurance
Requires-Python: >=3.8
